testsemrelease/__init__.py
testsemr-0.6.11.dist-info/METADATA
testsemr-0.6.11.dist-info/WHEEL
testsemr-0.6.11.dist-info/RECORD
